LICENSE
MANIFEST.in
PACKAGE.rst
README.md
setup.cfg
setup.py
deeplearning2020/__init__.py
deeplearning2020/datasets.py
deeplearning2020/helpers.py
deeplearning2020/submission.py
deeplearning2020.egg-info/PKG-INFO
deeplearning2020.egg-info/SOURCES.txt
deeplearning2020.egg-info/dependency_links.txt
deeplearning2020.egg-info/not-zip-safe
deeplearning2020.egg-info/requires.txt
deeplearning2020.egg-info/top_level.txt
tests/test_deeplearning2020.py